{"yield": null, "nutritionEstimates": [], "prepTimeInSeconds": 600, "totalTime": "1 hr 10 min", "images": [{"hostedSmallUrl": "http://lh3.ggpht.com/sBVkKdXY5qMchB0plim7Ikunxm4tCL1qPy_fnjvfH6wXrAjuVMQlLvnFu8jGXqNxQh9qS66GqMyLPqeJZHpC=s90", "hostedMediumUrl": "http://lh3.ggpht.com/sBVkKdXY5qMchB0plim7Ikunxm4tCL1qPy_fnjvfH6wXrAjuVMQlLvnFu8jGXqNxQh9qS66GqMyLPqeJZHpC=s180", "hostedLargeUrl": "http://lh3.ggpht.com/sBVkKdXY5qMchB0plim7Ikunxm4tCL1qPy_fnjvfH6wXrAjuVMQlLvnFu8jGXqNxQh9qS66GqMyLPqeJZHpC=s360", "imageUrlsBySize": {"90": "http://lh4.ggpht.com/Kot2dF9jG1sDMyBe53ulkxGtVhsr2riqTd_5Ub2EsT5H4TLrgUc8gMJAA3zTeDq5RkX9kU-El6xG5bhTDVM42-U=s90-c", "360": "http://lh4.ggpht.com/Kot2dF9jG1sDMyBe53ulkxGtVhsr2riqTd_5Ub2EsT5H4TLrgUc8gMJAA3zTeDq5RkX9kU-El6xG5bhTDVM42-U=s360-c"}}], "name": "Chicken Hot Pot", "source": {"sourceDisplayName": "China Sichuan Food", "sourceSiteUrl": "chinasichuanfood.com", "sourceRecipeUrl": "http://www.chinasichuanfood.com/spicy-chicken-hot-pot/"}, "prepTime": "10 Min", "id": "Chicken-Hot-Pot-608516", "ingredientLines": ["One pound chicken, add more chicken feet or wings or any other parts you like", "2 tablespoon vegetable oil", "2 large pig bones", "1 tablespoon broad bean paste (Doubanjiang)", "1 teaspoon Sichuan Peppercorn", "1 tablespoon dried chili pepper", "Several chunks of cassia bark", "\u00bd teaspoon of fennel", "Several cloves of garlic sliced", "One small section of ginger sliced", "3 teaspoon salt", "Sesame oil", "Chicken essence"], "cookTime": "1 Hr", "attribution": {"html": "<a href='http://www.yummly.co/recipe/Chicken-Hot-Pot-608516'>Chicken Hot Pot recipe</a> information powered by <img alt='Yummly' src='https://static.yummly.co/api-logo.png'/>", "url": "http://www.yummly.co/recipe/Chicken-Hot-Pot-608516", "text": "Chicken Hot Pot recipes: information powered by Yummly", "logo": "https://static.yummly.co/api-logo.png"}, "numberOfServings": 4, "totalTimeInSeconds": 4200, "attributes": {"course": ["Main Dishes"], "cuisine": ["Chinese", "Asian"]}, "cookTimeInSeconds": 3600, "flavors": {}, "rating": 3}