{"yield": "1 Kg", "nutritionEstimates": [], "prepTimeInSeconds": 1200, "totalTime": "20 min", "images": [{"hostedSmallUrl": "http://lh5.ggpht.com/imqoejjzU-GfTdOXinIZ5mJRfysHrvBAtg0hQo6_3Z-YzvvHk5V1CErgHdl-eQ8Yj5UC-vHBEcItqYLtAmda08c=s90", "hostedMediumUrl": "http://lh5.ggpht.com/imqoejjzU-GfTdOXinIZ5mJRfysHrvBAtg0hQo6_3Z-YzvvHk5V1CErgHdl-eQ8Yj5UC-vHBEcItqYLtAmda08c=s180", "hostedLargeUrl": "http://lh5.ggpht.com/imqoejjzU-GfTdOXinIZ5mJRfysHrvBAtg0hQo6_3Z-YzvvHk5V1CErgHdl-eQ8Yj5UC-vHBEcItqYLtAmda08c=s360", "imageUrlsBySize": {"90": "http://lh6.ggpht.com/JTpyyX6QQ8t4gFsvo2WSfW02K7hdVO0yUs3-nRiTYXLRpUHmfkSZ0eAYjYOyjbrXE2FmXU46JCQ8hSrvDqMIlA=s90-c", "360": "http://lh6.ggpht.com/JTpyyX6QQ8t4gFsvo2WSfW02K7hdVO0yUs3-nRiTYXLRpUHmfkSZ0eAYjYOyjbrXE2FmXU46JCQ8hSrvDqMIlA=s360-c"}}], "name": "Jama Masjid wala Mutton Korma", "source": {"sourceDisplayName": "Swati's Kitchen", "sourceSiteUrl": "swatisani.net", "sourceRecipeUrl": "http://swatisani.net/kitchen/recipe/jama-masjid-wala-mutton-korma/"}, "prepTime": "20 Min", "id": "Jama-Masjid-wala-Mutton-Korma-1010114", "ingredientLines": ["Mutton 1", "Onion, chopped 2 Large", "Ghee 10-12 Tbsp", "Ginger Paste 2 Tbsp", "Garlic paste 2 Tbsp", "Coriander seeds 2 Tbsp", "Black pepper whole 15-20", "Whole red Chillies 3-4", "Cloves 6", "Turmeric \u00bc Tsp", "Yogurt 1 cup (whipped)", "Mace 1/2 Tsp (ground)", "Green cardamom powder \u00bd Tsp", "Saffron (a few strands) dissolved in milk", "Kewra essence 1/4th Tsp", "Cream 4-5 tbsp", "Salt 1 Tsp (or to taste)", "Brown the onion in ghee and coarsely grind it.", "Grind coriander seed, black pepper whole, chilies and clove in the grinder to a fine powder.", "Grind coriander seed, black pepper whole, chilies and clove in the grinder to a fine powder.", "Grind coriander seed, black pepper whole, chilies and clove in the grinder to a fine powder.", "Grind coriander seed, black pepper whole, chilies and clove in the grinder to a fine powder."], "attribution": {"html": "<a href='http://www.yummly.co/recipe/Jama-Masjid-wala-Mutton-Korma-1010114'>Jama Masjid wala Mutton Korma recipe</a> information powered by <img alt='Yummly' src='https://static.yummly.co/api-logo.png'/>", "url": "http://www.yummly.co/recipe/Jama-Masjid-wala-Mutton-Korma-1010114", "text": "Jama Masjid wala Mutton Korma recipes: information powered by Yummly", "logo": "https://static.yummly.co/api-logo.png"}, "numberOfServings": 1, "totalTimeInSeconds": 1200, "attributes": {"course": ["Main Dishes"], "cuisine": ["Indian"]}, "flavors": {}, "rating": 3}