{"yield": "serves 4", "nutritionEstimates": [], "totalTime": "55 min", "images": [{"hostedSmallUrl": "http://lh3.ggpht.com/y1sfU_-8AUthEzxPBuPg4x87RVpeEzdYUZSHhCOg4Namg_R6FNGQ5xy6fqBXuRle4dd_NRnVPWsOw6PUvZOo=s90", "hostedMediumUrl": "http://lh3.ggpht.com/y1sfU_-8AUthEzxPBuPg4x87RVpeEzdYUZSHhCOg4Namg_R6FNGQ5xy6fqBXuRle4dd_NRnVPWsOw6PUvZOo=s180", "hostedLargeUrl": "http://lh3.ggpht.com/y1sfU_-8AUthEzxPBuPg4x87RVpeEzdYUZSHhCOg4Namg_R6FNGQ5xy6fqBXuRle4dd_NRnVPWsOw6PUvZOo=s360", "imageUrlsBySize": {"90": "http://lh6.ggpht.com/d7Vj6u10s_pKNOFWUgkV_p-nuf78R83QauzxxICVZARNXZf0yuyUVxsOtJGn38XqTmtF5JWpp3D_RlIBLahD=s90-c", "360": "http://lh6.ggpht.com/d7Vj6u10s_pKNOFWUgkV_p-nuf78R83QauzxxICVZARNXZf0yuyUVxsOtJGn38XqTmtF5JWpp3D_RlIBLahD=s360-c"}}], "name": "Roasted Lamb Chops with Greek Salad", "source": {"sourceDisplayName": "Taste", "sourceSiteUrl": "http://blog.williams-sonoma.com", "sourceRecipeUrl": "http://blog.williams-sonoma.com/roasted-lamb-chops-with-greek-salad/"}, "id": "Roasted-lamb-chops-with-greek-salad-370356", "ingredientLines": ["2 racks of lamb, each 7 or 8 ribs and 1 1/2-2 lb., frenched by butcher", "4 cloves garlic, thinly sliced", "4 sprigs fresh rosemary, roughly chopped", "2 1/2 Tbs. extra-virgin olive oil", "Sea salt and ground pepper", "Sea salt and ground pepper", "Greek salad for serving (see below)", "1/2 cup extra-virgin olive oil", "1/4 cup small fresh oregano leaves", "1 1/2 tsp. grated lemon zest", "1 1/2 cups halved cherry tomatoes", "1 cup crumbled feta cheese", "1 cup salt-cured olives", "1/2 red onion, thinly sliced", "1/4 English cucumber, thinly sliced", "Salt and ground pepper", "Salt and ground pepper"], "attribution": {"html": "<a href='http://www.yummly.co/recipe/Roasted-lamb-chops-with-greek-salad-370356'>Roasted Lamb Chops with Greek Salad recipe</a> information powered by <img alt='Yummly' src='https://static.yummly.co/api-logo.png'/>", "url": "http://www.yummly.co/recipe/Roasted-lamb-chops-with-greek-salad-370356", "text": "Roasted Lamb Chops with Greek Salad recipes: information powered by Yummly", "logo": "https://static.yummly.co/api-logo.png"}, "numberOfServings": 4, "totalTimeInSeconds": 3300, "attributes": {"course": ["Main Dishes"], "cuisine": ["Mediterranean", "Greek"]}, "flavors": {}, "rating": 5}