{"yield": "yield: 1-1", "nutritionEstimates": [], "totalTime": "45 min", "images": [{"hostedSmallUrl": "http://lh5.ggpht.com/e-dI87NBKalpRypKWO-4TI7IjDMt5uX_-10swlfcE8ldNO04dmNfpPalHMKRhrlcytrjRuDxVqY2xiWXglPECQ=s90", "hostedMediumUrl": "http://lh5.ggpht.com/e-dI87NBKalpRypKWO-4TI7IjDMt5uX_-10swlfcE8ldNO04dmNfpPalHMKRhrlcytrjRuDxVqY2xiWXglPECQ=s180", "hostedLargeUrl": "http://lh5.ggpht.com/e-dI87NBKalpRypKWO-4TI7IjDMt5uX_-10swlfcE8ldNO04dmNfpPalHMKRhrlcytrjRuDxVqY2xiWXglPECQ=s360", "imageUrlsBySize": {"90": "http://lh6.ggpht.com/gf-7Tc7Lb1AV08Ft6ESSU9Ue_0BpRFVsN5jzUy25nMJ3N6mnoOPkIAbL56_Qki-ztcCeJTMSQVxOTzFE7E3Ib8Y=s90-c", "360": "http://lh6.ggpht.com/gf-7Tc7Lb1AV08Ft6ESSU9Ue_0BpRFVsN5jzUy25nMJ3N6mnoOPkIAbL56_Qki-ztcCeJTMSQVxOTzFE7E3Ib8Y=s360-c"}}], "name": "Shrimp Tempura", "source": {"sourceDisplayName": "Annie's Eats", "sourceSiteUrl": "http://www.annies-eats.com", "sourceRecipeUrl": "http://www.annies-eats.com/2010/04/19/shrimp-tempura/"}, "id": "Shrimp-Tempura-476110", "ingredientLines": ["1\u00bd qts. vegetable oil, for frying", "1-1\u00bd lbs. jumbo/colossal shrimp, peeled and deveined, tails left on", "1\u00bd cups all-purpose flour", "\u00bd cup cornstarch", "1 large egg", "1 cup vodka", "1 cup seltzer water", "Kosher salt", "\u00bc cup soy sauce", "3 tbsp. mirin", "1 tsp. sugar", "1 tsp. sesame oil", "1 clove garlic, minced or pressed", "2 tsp. grated fresh ginger", "1 green onion, finely chopped"], "attribution": {"html": "<a href='http://www.yummly.co/recipe/Shrimp-Tempura-476110'>Shrimp Tempura recipe</a> information powered by <img alt='Yummly' src='https://static.yummly.co/api-logo.png'/>", "url": "http://www.yummly.co/recipe/Shrimp-Tempura-476110", "text": "Shrimp Tempura recipes: information powered by Yummly", "logo": "https://static.yummly.co/api-logo.png"}, "numberOfServings": 1, "totalTimeInSeconds": 2700, "attributes": {"course": ["Main Dishes"], "cuisine": ["Japanese", "Asian"]}, "flavors": {}, "rating": 0}